Workbook

Sheet Kundenstamm Re
A1: Kundennummer | B1: Firmenwortlaut | C1: Firmentitel | D1: Firmentitel | E1: Straße | F1: PLZ/ORT | G1: UID Nr.- Kunde
A3: 100 | B3: Möbel-Gabl GmbH | E3: Industriezone 59 | F3: A-6460 Imst | G3: ATU 32519405
A4: =IF(ISBLANK(B3),"",A3+1) -> 101 | B4: IKEA Möbelvertrieb OHG | C4: Einrichtungshaus Innsbruck | E4: Amraser-See-Str 56c DEZ | F4: A-6020 Innsbruck | G4: ATU 19420008
A5: =IF(ISBLANK(B4),"",A4+1) -> 102 | B5: Kone AG | E5: Lembökgasse 61 | F5: A-1230 Wien | G5: ATU 14651205
A6: =IF(ISBLANK(B5),"",A5+1) -> 103 | B6: EWR Handelsgesellschaft m.b.H. | C6: Elektronik. Voller Service | E6: Großfeldstraße 10-14 | F6: A-6600 Reutte | G6: ATU 57443500
A7: =IF(ISBLANK(#REF!),"",A6+1) -> 104 | B7: Gitterle Christoph GmbH | C7: Tischlerei u Küchenstudio | E7: Fließerau 390 | F7: A-6500 Landeck | G7: ATU 53026005
A8: =IF(ISBLANK(B7),"",A7+1) -> 105 | B8: P.O. Montage- | C8: Vermittlungs-Service GmbH | E8: Rennweg 78-1 | F8: A-1030 Wien | G8: ATU 66549167
A9: =IF(ISBLANK(B8),"",A8+1) -> 106 | B9: Die Küchenprofis | C9: Schranz- Wolf Gmbh | E9: Kampleweg 2 | F9: A-6532 Prutz | G9: ATU63128323
A10: =IF(ISBLANK(B9),"",A9+1) -> 107 | B10: Fuchs Erwin | E10: Namlos 21 | F10: A-6623 Namlos | G10: Privat
A11: =IF(ISBLANK(B10),"",A10+1) -> 108 | B11: Dan Küchen | C11: Leitner Telfs | E11: Weißenbachgasse 1 | F11: A-6410 Telfs | G11: ATU66090589
A12: =IF(ISBLANK(B11),"",A11+1) -> 109 | B12: Kirschner Patrick | C12: Privat Kunde | E12: Gunesweg 17 | F12: A-6532 Ladis | G12: ATU06759934
A13: =IF(ISBLANK(B12),"",A12+1) -> 110 | B13: Thomas Schnegg | C13: Tischlerei | E13: Au 21 | F13: A-6492 Imsterberg | G13: ATU32538901
A14: =IF(ISBLANK(B13),"",A13+1) -> 111 | B14: Fischer Parket | C14: Ges.m.b.H & Co KG | E14: Lauterbach 12 | F14: A-5151 Nussdorf | G14: ATU35004400
A15: =IF(ISBLANK(B14),"",A14+1) -> 112 | B15: Vilbur | C15: Grupo Entre Vilbur 2013s.l | E15: Camino de los Vinateros 106 | F15: 28030 Madrid | G15: ESB86752573
A16: =IF(ISBLANK(B15),"",A15+1) -> 113 | B16: Schöpf Barbara | E16: Längenfeld 198 | F16: A-6444 Längenfeld | G16: Privat
A17: =IF(ISBLANK(B16),"",A16+1) -> 114 | B17: Angelika Fiegl | E17: Wassertalstraße 8 | F17: A-6430 Ötztal-Bahnhof | G17: Privat
A18: =IF(ISBLANK(B17),"",A17+1) -> 115 | B18: Schloß Fernstein GmbH | C18: Fam. Köhle | E18: Fernstein | F18: A-6465Nassereith | G18: Privat
A19: =IF(ISBLANK(B18),"",A18+1) -> 116 | B19: Kysella Margit | E19: Am Grettert16 | F19: A-6460 Imst | G19: Privat
A20: =IF(ISBLANK(B19),"",A19+1) -> 117 | B20: Egger Andreas u.Eva | E20: Griesackerweg 6 | F20: A-6423 Mötz | G20: Privat
A21: =IF(ISBLANK(B20),"",A20+1) -> 118 | B21: Petix e. U. | E21: Dollinger -Lager 7 | F21: A-6464 Tarrenz | G21: ATU67548825
A22: =IF(ISBLANK(B21),"",A21+1) -> 119 | B22: Karl Prugger | C22: Möbeltischlerei | E22: Staatsstraße 15 | F22: I-39024 Mals | G22: ATUIT01560760215
A23: =IF(ISBLANK(B22),"",A22+1) -> 120 | B23: Knorr Markus und Tanja | E23: Biburgerweg 3 | F23: DE 82205 Gilching | G23: Privat
A24: =IF(ISBLANK(B23),"",A23+1) -> 121 | B24: Gapp Elisabeth Ing. | E24: Blockau 62a | F24: A-6642 Stanzach | G24: Privat
A25: =IF(ISBLANK(B24),"",A24+1) -> 122 | B25: Seiler Adalbert | E25: Dorfstraße 3 | F25: A-6426 Roppen | G25: Privat
A26: =IF(ISBLANK(B25),"",A25+1) -> 123 | B26: Gruber Franz | E26: Stanzach Nr. 122 | F26: 6642 Stanzach | G26: Privat
A27: =IF(ISBLANK(B27),"",A26+1) -> 124 | B27: Prantl Peter | E27: Am Weinberg 16 | F27: 6460 Imst | G27: Privat
A28: =IF(ISBLANK(#REF!),"",A27+1) -> 125 | B28: Pohl Hansjörg | E28: Wiesenweg 5 | F28: 6426 Roppen | G28: Privat
A29: =IF(ISBLANK(B28),"",A28+1) -> 126 | B29: Schmid Andreas | C29: Haus Ambiente Austria | E29: Niederthai Nr.142 | F29: 6441 Umhausen | G29: ATU 66667822
A30: =IF(ISBLANK(B29),"",A29+1) -> 127 | B30: Eiter Christine | E30: Wald-Untergasse 25 | F30: 6471 Arzl im Pitztal | G30: Privat
A31: =IF(ISBLANK(B30),"",A30+1) -> 128 | B31: Tiefenbrunner Manfred | C31: Tischlerei GmbH. | E31: Schulgasse 12 | F31: 6464 Tarrenz | G31: ATU 63118147
A32: =IF(ISBLANK(B31),"",A31+1) -> 129 | B32: Reich Patrick | E32: Brunnwald 403 | F32: 6465 Nassereith
A33: =IF(ISBLANK(B32),"",A32+1) -> 130 | B33: Nickmann Paul | E33: Müllerhofweg 5 | F33: 6632 Ehrwald
A34: =IF(ISBLANK(B33),"",A33+1) -> 131 | B34: Schöpf Benjamin, Katharina | E34: Habichen 123 | F34: 6433 Ötz
A35: =IF(ISBLANK(B34),"",A34+1) -> 132 | B35: Kofler Thomas | E35: Brand | F35: 6622 Berwang | G35: Privat
A36: =IF(ISBLANK(B35),"",A35+1) -> 133 | B36: Tschiderer Rene | E36: Josef-Dreier-Weg 3 | F36: A-6671 Weissenbach am Lech | G36: Privat
A37: =IF(ISBLANK(B36),"",A36+1) -> 134 | B37: Lutz Heidi | E37: Brunnwald 411 | F37: A-6465 Nassereith | G37: Privat
A38: =IF(ISBLANK(B37),"",A37+1) -> 135 | B38: Oldenbourg Paul | E38: Stanzach Nr. 86a | F38: A-6642 Stanzach | G38: Privat
A39: =IF(ISBLANK(B38),"",A38+1) -> 136 | B39: Marin Rogic | E39: Stanzach Nr. 74 | F39: A-6642 Stanzach | G39: Privat
A40: =IF(ISBLANK(B39),"",A39+1) -> 137 | B40: Schäfer Hubert | E40: Stanzach Nr. 151 | F40: A-6642 Stanzach | G40: Privat
A41: =IF(ISBLANK(B40),"",A40+1) -> 138 | B41: Köck Gertrud | E41: Stanzach Nr. 148 | F41: A-6642 Stanzach | G41: Privat
A42: =IF(ISBLANK(B41),"",A41+1) -> 139 | B42: Lutz Silvia und Peter | E42: Blockau 19 | F42: A-6642 Stanzach | G42: Privat
A43: =IF(ISBLANK(B42),"",A42+1) -> 140 | B43: Reinpold Horst | E43: Gipsmühlenstraße 43b | F43: A-6600 Breitenwang
A44: =IF(ISBLANK(B43),"",A43+1) -> 141 | B44: Markus Haselsberger | E44: Blockau 74 | F44: A-6642 Stanzach | G44: Privat
A45: =IF(ISBLANK(B44),"",A44+1) -> 142 | B45: Karlen Regina | E45: Metallwerk-Planseestraße 14 | F45: A-6600 Breitenwang | G45: Privat
A46: =IF(ISBLANK(B45),"",A45+1) -> 143 | B46: Gapp Charlotte | E46: Blockau 110 | F46: A-6642 Stanzach | G46: Privat
A47: =IF(ISBLANK(B46),"",A46+1) -> 144 | B47: Singer Monika | E47: Hausnummer 68 | F47: A-6644 Elmen | G47: Privat
A48: =IF(ISBLANK(B47),"",A47+1) -> 145 | B48: Familienskilift | E48: Hausnummer 6 | F48: A-6642 Stanzach
A49: =IF(ISBLANK(B48),"",A48+1) -> 146 | B49: Knitel Michael | E49: Hausnummer 152 | F49: A-6642 Stanzach | G49: Privat
A50: =IF(ISBLANK(B49),"",A49+1) -> 147 | B50: Wolfram Frick | E50: Bichl 9 | F50: A-6611 Heiterwang | G50: ATU 48210305
A51: =IF(ISBLANK(B50),"",A50+1) -> 148 | B51: Fam. Urthaler | E51: Neder 40 | F51: A-6095 Grinzens | G51: Privat
A52: =IF(ISBLANK(B51),"",A51+1) -> 149 | B52: Wolfgang Bauer | E52: Blockau | F52: A-6642 Stanzach | G52: Privat
A53: =IF(ISBLANK(B52),"",A52+1) -> 150 | B53: Markt Alexander | E53: Siedlungsweg 7 | F53: A-6671 Weissenbach am Lech | G53: Privat
A54: =IF(ISBLANK(B53),"",A53+1) -> 151 | B54: La Soa Chalets & Eventlodge | E54: Schattwald 80 | F54: A-6677 Schattwald | G54: ATU 69923602
A55: =IF(ISBLANK(B54),"",A54+1) -> 152 | B55: Amtmann Mario | E55: Blockau 89 | F55: A-6642 Stanzach | G55: Privat
A56: =IF(ISBLANK(B55),"",A55+1) -> 153 | B56: Preisser Eddy | E56: Hausnummer 18 | F56: A-6642 Stanzach | G56: Privat
A57: =IF(ISBLANK(B56),"",A56+1) -> 154 | B57: Agerer Angelika und Joachim | E57: Hauptstraße 1 | F57: A-6464 Tarrenz | G57: Privat
A58: =IF(ISBLANK(B57),"",A57+1) -> 155 | B58: Jungbauernschaft Vorderhornbach | E58: Vorderhornbach Nr. 11 | F58: A-6645 Vorderhornbach | G58: Privat
A59: =IF(ISBLANK(B58),"",A58+1) -> 156 | B59: Fam. Feistenauer | E59: Dorfstraße 21 | F59: A-6604 Höfen | G59: Privat
A60: =IF(ISBLANK(B60),"",A59+1) -> 157 | B60: Posch Hubert | E60: Oberhof 19 | F60: A-6671 Weissenbach am Lech | G60: Privat
A61: =IF(ISBLANK(B61),"",A60+1) -> 158 | B61: SV Stanzach | C61: z.H. Leopold Lechleitner | E61: Hausnummer 133 | F61: A-6642 Stanzach | G61: Privat
A62: =IF(ISBLANK(#REF!),"",A61+1) -> 159 | B62: Brandl Andreas | E62: Dorfstraße 7 | F62: A-6604 Höfen | G62: Privat
A63: =IF(ISBLANK(B62),"",A62+1) -> 160 | B63: Köck Daniel | E63: Schröfle 103 | F63: A-6645 Vorderhornbach | G63: Privat
A64: =IF(ISBLANK(B63),"",A63+1) -> 161 | B64: Bärbel Liebich | C64: C/o Eva Liebich | E64: Rütgerweg 3 | F64: D-22763 Hamburg | G64: Privat
A65: =IF(ISBLANK(B64),"",A64+1) -> 162 | B65: Falger Nadja und Jürgen | E65: Blockau 15 | F65: A-Stanzach | G65: Privat
A66: =IF(ISBLANK(B65),"",A65+1) -> 163 | B66: Hotel Föhrenhof | C66: Haider Alexandra | E66: Bödele 17 | F66: A-Stanzach | G66: ATU 737 66 178
A67: =IF(ISBLANK(B66),"",A66+1) -> 164 | B67: Greil Anette und Christian | E67: Griesegg 20 | F67: A-6464 Tarrenz | G67: Privat
A68: =IF(ISBLANK(B67),"",A67+1) -> 165 | B68: Kofler Christoph | E68: Obtarrenz 12 | F68: A-6464 Tarrenz | G68: Privat
A69: =IF(ISBLANK(B68),"",A68+1) -> 166 | B69: Köpfle Karlheinz | E69: Schöfle 104 | F69: A-6645 Vorderhornbach | G69: Privat
A70: =IF(ISBLANK(B69),"",A69+1) -> 167 | B70: Lutz Michael | E70: Hauptstraße 1 | F70: A-6464 Tarrenz | G70: Privat
A71: =IF(ISBLANK(B70),"",A70+1) -> 168 | B71: Gratl Werner | F71: A-6600 Reutte | G71: Privat
A72: =IF(ISBLANK(B71),"",A71+1) -> 169 | B72: Ausserferner Betonwerk GesmbH u. CoKG | E72: Sportplatzstraße 4 | F72: A-6600 Lechaschau | G72: ATU32957306
A73: =IF(ISBLANK(B72),"",A72+1) -> 170 | B73: Lang Rudolf | E73: Nr. 116 | F73: A-6645 Vorderhornbach | G73: Privat
A74: =IF(ISBLANK(B73),"",A73+1) -> 171 | B74: Reich Bernhard | E74: Nr.68f | F74: A-6654 Holzgau | G74: Privat
A75: =IF(ISBLANK(B74),"",A74+1) -> 172 | B75: WEG Lutz | E75: Brunnwald 411 | F75: A-6465 Nassereith | G75: Privat
A76: 173 | B76: Winkler Michael | E76: Dorf 18 | F76: A-6642 Stanzach | G76: Privat
A77: 174 | B77: Gemeinde Stanzach | E77: Dorf 1 | F77: A-6642 Stanzach | G77: ATU 47374103
A78: 175 | B78: Schwarz Michael | E78: Rauth 44 | F78: A-6642 Stanzach | G78: ATU 72130339
A79: 176 | B79: Köpfle Thorsten | E79: Am Schröfle 92 | F79: A-6645 Vorderhornbach | G79: ATU 66376334
A80: =IF(ISBLANK(B79),"",A79+1) -> 177 | B80: Schratz Erwin | E80: Prof. Dengel Str. 31 | F80: A-6600 Reutte | G80: Privat
A81: =IF(ISBLANK(B80),"",A80+1) -> 178 | B81: Architekturbüro Dejaco | E81: Ehrenbergstr 50 | F81: A-6600 Reutte
A82: =IF(ISBLANK(B81),"",A81+1) -> 179 | B82: Posch Peter | F82: A-6460 Imst | G82: Privat
A83: =IF(ISBLANK(B82),"",A82+1) -> 180 | B83: Stelzhammer Wilko | F83: A-6604 Höfen | G83: Privat
A84: =IF(ISBLANK(B83),"",A83+1) -> 181 | B84: Pension Hornbachstüberl | C84: Lechleitner Norbert | E84: Hnr.:30 | F84: A-6646 Hinterhornbach | G84: ATU 64469505
A85: =IF(ISBLANK(B84),"",A84+1) -> 182 | B85: Gemeinde Hinterhornbach | E85: Hnr: 18 | F85: A-6646 Hinterhornbach
A86: =IF(ISBLANK(B85),"",A85+1) -> 183 | B86: Paulmichl Fritz | E86: Nr. 64 | F86: A-6645 Vorderhornbach | G86: Privat
A87: =IF(ISBLANK(B86),"",A86+1) -> 184 | B87: Jäger Roland | E87: Ing. Kastner Straße 161 | F87: A-6465 Nassereith | G87: Privat
A88: =IF(ISBLANK(B87),"",A87+1) -> 185 | B88: Barbist Michael | E88: Kirchmairstraße 2 | F88: A-6610 Wängle | G88: Privat
A89: =IF(ISBLANK(B88),"",A88+1) -> 186 | B89: Hüttig Marion und Tobias | E89: Blockau 36a | F89: A-6642 Stanzach | G89: Privat
A90: =IF(ISBLANK(B89),"",A89+1) -> 187 | B90: Klier Werner und Irene | E90: Siedlung 96 | F90: A-6645 Vorderhornbach | G90: Privat
A91: =IF(ISBLANK(B90),"",A90+1) -> 188 | B91: Bader Sebastian | E91: Hnr. 22a | F91: A-6646 Hinterhornbach | G91: Privat
A92: =IF(ISBLANK(B91),"",A91+1) -> 189 | B92: Tröstl Carina und Dieter | E92: Hnr. 99 | F92: A-6644 Elmen | G92: Privat
A93: =IF(ISBLANK(B92),"",A92+1) -> 190 | B93: Winkler - Perle Silvia | E93: Dorf 18 | F93: A-6642 Stanzach | G93: Privat
A94: =IF(ISBLANK(B94),"",A93+1) -> 191 | B94: Winkler Martin | E94: Rain 9 | F94: A-Stanzach | G94: Privat
A95: =IF(ISBLANK(#REF!),"",A94+1) -> 192 | B95: Gundolf Reinhold | E95: Eggmahd 561 | F95: A-6473 Wenns | G95: Privat
A96: =IF(ISBLANK(B95),"",A95+1) -> 193 | B96: Gundolf Evelyn | E96: Dorfstraße 40a | F96: A-6471 Arzl i. Pitztal | G96: Privat
A97: =IF(ISBLANK(B96),"",A96+1) -> 194 | B97: Werner Schönherr | E97: Badergasse | F97: A-645 Nassereith | G97: Privat
A98: =IF(ISBLANK(B97),"",A97+1) -> 195 | B98: Frischhut Stefan | E98: Ehrenbergstraße 18 | F98: A-6600 Reutte | G98: Privat
A99: =IF(ISBLANK(B98),"",A98+1) -> 196 | B99: Hollauf Patrick | E99: Palmersbachweg 26 | F99: A-6460 Imst | G99: Privat
A100: =IF(ISBLANK(B99),"",A99+1) -> 197 | B100: Nessler Fenster Türen Vertriebs-Gesellschaft m.b.H. | E100: Lechtalerstraße 45 | F100: A-6600 Lechaschau | G100: ATU61130127
A101: =IF(ISBLANK(B100),"",A100+1) -> 198 | B101: Langebner Stefanie, Kappeller Benjamin | E101: Stockach 19b | F101: A-6653 Bach | G101: Privat
...

Sheet Rechnung inkl. MWST
A6: Holzbau Lutz OG, Am Sportplatz 3, 6642 Stanzach
A8: =VLOOKUP(G9,'Kundenstamm Re'!A:K,2,FALSE)& " " -> #N/A | F8: Rechnungsnr.: | G8: XXX
A9: =VLOOKUP(G9,'Kundenstamm Re'!A:K,3,FALSE)& " " -> #N/A | F9: Kundennr.: | G9: XXX
A10: =VLOOKUP(G9,'Kundenstamm Re'!A:K,4,FALSE)& " " -> #N/A | F10: Datum: | G10: =TODAY() -> 46169
A11: =VLOOKUP(G9,'Kundenstamm Re'!A:K,5,FALSE)& " " -> #N/A | F11: UID Nr.- Kunde: | G11: =VLOOKUP(G9,'Kundenstamm Re'!A:K,7,FALSE)& " " -> #N/A
A12: =VLOOKUP(G9,'Kundenstamm Re'!A:K,6,FALSE)& " " -> #N/A | F12: Seite:
A17: Rechnung
A19: Nr.: | B19: =G8 -> XXX
A20: Lieferadresse: | D20: XXX | F20: Leistungszeitraum:
A21: Betreff: | D21: XXX | F21: XXX
A23: POS. | B23: MENGE | C23: EH | D23: BEZEICHNUNG | F23: PREIS/EH | G23: GESAMT
G25: =B25*F25 -> 0
G26: =B26*F26 -> 0
G27: =B27*F27 -> 0
G28: =B28*F28 -> 0
G29: =B29*F29 -> 0
D31: Nettobetrag | G31: =SUM(G24:G29) -> 0
D32: zuzüglich 20% Mwst. | G32: =G33-G31 -> 0
D33: Rechnungsbetrag brutto | G33: =G31*1.2 -> 0
D35: Zahlbar nach Erhalt der Rechnung netto Kassa.
D36: Bei Überweisung mittels Internet-Banking tragen Sie bitte im Feld | G36: =B36*F36 -> 0
D37: "Verwendungszweck" die Rechnungsnummer ein.
D39: Vielen Dank für Ihren Auftrag.

Sheet Rechnung exkl. MWST
A6: Holzbau Lutz OG, Am Sportplatz 3, 6642 Stanzach
A8: =VLOOKUP(G9,'Kundenstamm Re'!A:K,2,FALSE)& " " -> #N/A | F8: Rechnungsnr.: | G8: XXX
A9: =VLOOKUP(G9,'Kundenstamm Re'!A:K,3,FALSE)& " " -> #N/A | F9: Kundennr.: | G9: XXX
A10: =VLOOKUP(G9,'Kundenstamm Re'!A:K,4,FALSE)& " " -> #N/A | F10: Datum: | G10: =TODAY() -> 46169
A11: =VLOOKUP(G9,'Kundenstamm Re'!A:K,5,FALSE)& " " -> #N/A | F11: UID Nr.- Kunde: | G11: =VLOOKUP(G9,'Kundenstamm Re'!A:K,7,FALSE)& " " -> #N/A
A12: =VLOOKUP(G9,'Kundenstamm Re'!A:K,6,FALSE)& " " -> #N/A | F12: Seite:
A17: Rechnung
A19: Nr.: | B19: =G8 -> XXX
A20: Lieferadresse: | D20: XXX | F20: Leistungszeitraum:
A21: Betreff: | D21: XXX | F21: XXX.23
A23: POS. | B23: MENGE | C23: EH | D23: BEZEICHNUNG | F23: PREIS/EH | G23: GESAMT
A25: 1 | G25: =B25*F25 -> 0
G26: =B26*F26 -> 0
G27: =B27*F27 -> 0
G28: =B28*F28 -> 0
G29: =B29*F29 -> 0
D31: Rechnungsbetrag netto | G31: =SUM(G25:G29) -> 0
D34: Bemerkung: Bauleistung im Sinne § 19a USTG.
D35: Zahlbar nach Erhalt der Rechnung netto Kassa.
D36: Bei Überweisung mittels Internet-Banking tragen Sie bitte im Feld | G36: =B36*F36 -> 0
D37: "Verwendungszweck" die Rechnungsnummer ein.
D39: Vielen Dank für Ihren Auftrag.

Sheet Zahlungserinnerung
A6: Holzbau Lutz OG, Am Sportplatz 3, 6642 Stanzach
A8: =VLOOKUP(G9,'Kundenstamm Re'!A:K,2,FALSE)& " " -> #N/A | F8: Rechnungsnr.: | G8: XXX
A9: =VLOOKUP(G9,'Kundenstamm Re'!A:K,3,FALSE)& " " -> #N/A | F9: Kundennr.: | G9: XXX
A10: =VLOOKUP(G9,'Kundenstamm Re'!A:K,4,FALSE)& " " -> #N/A | F10: Datum: | G10: =TODAY() -> 46169
A11: =VLOOKUP(G9,'Kundenstamm Re'!A:K,5,FALSE)& " " -> #N/A | F11: UID Nr.- Kunde: | G11: =VLOOKUP(G9,'Kundenstamm Re'!A:K,7,FALSE)& " " -> #N/A
A12: =VLOOKUP(G9,'Kundenstamm Re'!A:K,6,FALSE)& " " -> #N/A | F12: Seite: | G12: 1 von 1
A17: Zahlungserinnerung
A19: Wir erlauben uns, Ihre Aufmerksamkeit auf die unten angeführten fälligen Rechnungen zu lenken und
A20: ersuchen Sie, diese zu begleichen.
A21: Sollten Sie in der Zwischenzeit bereits Zahlungen geleistet haben, bitten wir Sie,
A22: dieses Schreiben als gegenstandslos.
A24: Re.nummer | C24: Re. Datum | D24: fällig am | E24: Rechnungsbetrag | G24: Mahnstufe
G26: =B26*F26 -> 0
G27: =B27*F27 -> 0
D29: Summe | F29: =SUM(F25:F27) -> 0
D30: Verzugszinsen | F30: 3
D31: Fälliger Saldo | F31: =SUM(F29:F30) -> 3
D34: Bei Überweisung mittels Internet-Banking tragen Sie bitte im Feld | G34: =B34*F34 -> 0
D35: "Verwendungszweck" die Rechnungsnummer ein.
A38: Zahlungseingänge wurden bis zum xx.xx.2018 berücksichtigt.
A40: Zahlung erbeten an Montagen Lutz OG zugunsten Konto IBAN: AT21 2050 2000 0084 9588
A41: bei der Sparkasse Imst AG BIC: SPIMAT21.

Sheet Zahlungsüberweisung
A1: Holzbau Lutz OG
A2: AT21 2050 2000 0084 9588
A3: SPIMAT 21XXX | W3: ='Rechnung inkl. MWST'!#REF! -> #REF!
A5: KNr.: | C5: ='Rechnung inkl. MWST'!G9 -> XXX | H5: RNr.: | J5: ='Rechnung inkl. MWST'!B19 -> XXX

Sheet Kuvert

Sheet Vorlage Firmenpap

Sheet Vorlage Firmenpapier Angebot
G41: =B41*F41 -> 0
A52: Montagen Lutz OG, 6642 Stanzach, Am Sportplatz 3
A53: Mobil: 0699/191 68 685, E-Mail: info@holzbau-lutz.at

Sheet Adresszeile
A6: Holzbau Lutz OG, Am Sportplatz 3, 6642 Stanzach
A9: XXX
A11: XXX
A12: XXX

Sheet Briefvorlage
A6: Holzbau Lutz OG, Am Sportplatz 3, 6642 Stanzach
A8: An
A9: XXX
A10: XXX | F10: Datum: | G10: =TODAY() -> 46169
A11: XXX
A12: XXX
A17: Betreff:

Sheet TR
A1: Wir bitten Sie höflichst zum o.a.BV.
A2: um eine 1. Teilrechnung in der Höhe von
